helix/WIP/ai.py
helix/WIP/evoprotgrad.py
helix/WIP/foldseek.py
helix/WIP/pocketgen.py
helix/WIP/proteinmpnn.py
helix/WIP/rosetta.py
helix/WIP/synthesis.py
helix/WIP/analysis/virtual_dms.py
helix/WIP/finetuning/common.py
helix/WIP/finetuning/inference.py
helix/WIP/finetuning/train.py
helix/WIP/finetuning/train_cli.py
helix/WIP/finetuning/utils.py
helix/WIP/longread_umi/__init__.py
helix/WIP/longread_umi/main.py
helix/WIP/sequence/deprecated.py
helix/WIP/sequence/scorer copy.py
helix/core/__init__.py
helix/core/images.py
helix/core/volumes.py
helix/functions/chai.py
helix/functions/diffdock.py
helix/functions/embedding.py
helix/functions/esmfold.py
helix/functions/mmseqs.py
helix/functions/unimol.py
helix/functions/scoring/protein.py
helix/utils/filecache.py
helix/utils/molecule.py
helix/utils/sequence.py
helix/utils/structure.py
helixbio-0.3.0.dist-info/LICENSE
helixbio-0.3.0.dist-info/METADATA
helixbio-0.3.0.dist-info/WHEEL
helixbio-0.3.0.dist-info/top_level.txt
helixbio-0.3.0.dist-info/RECORD
