Metadata-Version: 2.1
Name: helixbio
Version: 0.3.0
Summary: Add your description here
Requires-Python: >=3.9
License-File: LICENSE
Requires-Dist: biopython >=1.84
Requires-Dist: loguru >=0.7.2
Requires-Dist: modal >=0.64.232
Requires-Dist: pandas >=2.2.3
